alt2py/__init__.py
alt2py/_utils/Aggregators.py
alt2py/_utils/Functions.py
alt2py/_utils/OTaaT_extender.py
alt2py/_utils/__init__.py
alt2py/_utils/configuration_generator.py
alt2py/_utils/convert_yxdb_inputs.py
alt2py/_utils/input_converter.py
alt2py/_utils/scraper.py
alt2py/tools/Config.py
alt2py/tools/ReadYXDB.py
alt2py/tools/__init__.py
alt2py/tools/boilerplate.py
alt2py/tools/clean.py
alt2py/tools/crosstab.py
alt2py/tools/datetime.py
alt2py/tools/fileinput.py
alt2py/tools/fileoutput.py
alt2py/tools/filter.py
alt2py/tools/formula.py
alt2py/tools/generaterows.py
alt2py/tools/impute.py
alt2py/tools/join.py
alt2py/tools/joinmultiple.py
alt2py/tools/limit.py
alt2py/tools/multifieldbin.py
alt2py/tools/multifieldformula.py
alt2py/tools/multirowformula.py
alt2py/tools/oversample.py
alt2py/tools/recordid.py
alt2py/tools/regex.py
alt2py/tools/sample.py
alt2py/tools/select.py
alt2py/tools/selectrecords.py
alt2py/tools/sort.py
alt2py/tools/summarise.py
alt2py/tools/textinput.py
alt2py/tools/texttocolumns.py
alt2py/tools/tile.py
alt2py/tools/transpose.py
alt2py/tools/union.py
alt2py/tools/unique.py
alt2py/tools/xmlparse.py
alt2py-0.0.3.dist-info/LICENSE
alt2py-0.0.3.dist-info/METADATA
alt2py-0.0.3.dist-info/WHEEL
alt2py-0.0.3.dist-info/top_level.txt
alt2py-0.0.3.dist-info/RECORD
