Metadata-Version: 2.1
Name: alt2py
Version: 0.0.3
Summary: A package that provides simplified data prep and blending functionality.
Home-page: https://github.com/M-Michelini/alt2py/tree/master#readme
Author: Michael Michelini
Author-email: mmichelini1997@gmail.com
Project-URL: Bug Tracker, https://github.com/M-Michelini/alt2py/issues
Classifier: Programming Language :: Python :: 3
Classifier: License :: OSI Approved :: MIT License
Classifier: Operating System :: OS Independent
Requires-Python: >=3.6
License-File: LICENSE
